ModbusSharedMemory/__init__.py
ModbusSharedMemory/client_server.py
ModbusSharedMemory/memory.py
ModbusSharedMemory-0.1.1.dist-info/LICENSE
ModbusSharedMemory-0.1.1.dist-info/METADATA
ModbusSharedMemory-0.1.1.dist-info/WHEEL
ModbusSharedMemory-0.1.1.dist-info/top_level.txt
ModbusSharedMemory-0.1.1.dist-info/RECORD
