Metadata-Version: 2.1
Name: ModbusSharedMemory
Version: 0.1.1
Summary: Shared memory concept known from PLC manner implemented over uModbus framework.
Home-page: https://github.com/igoras1993/modbus_shared_memory
Author: Igor Kantorski
Author-email: igor.kantorski@gmail.com
License: UNKNOWN
Platform: UNKNOWN
Classifier: Development Status :: 2 - Pre-Alpha
Classifier: Intended Audience :: Developers
Classifier: Intended Audience :: Telecommunications Industry
Classifier: License :: OSI Approved :: MIT License
Classifier: Operating System :: OS Independent
Classifier: Programming Language :: Python :: 3
Classifier: Topic :: Home Automation
Classifier: Topic :: Scientific/Engineering :: Human Machine Interfaces
Classifier: Topic :: Scientific/Engineering :: Interface Engine/Protocol Translator
Classifier: Topic :: Software Development :: Libraries :: Python Modules
